[
  {
    "id": 1,
    "original": "International Nurses Day",
    "score": 65,
    "is_kid_friendly": true
  },
  {
    "id": 2,
    "original": "National Limerick Day",
    "score": 80,
    "is_kid_friendly": true
  },
  {
    "id": 3,
    "original": "National Nutty Fudge Day",
    "score": 80,
    "is_kid_friendly": true
  },
  {
    "id": 4,
    "original": "National Fibromyalgia Awareness Day",
    "score": 25,
    "is_kid_friendly": false
  },
  {
    "id": 5,
    "original": "Fatima Day",
    "score": 45,
    "is_kid_friendly": false
  }
]