[
  {
    "id": 1,
    "original": "National Hot Chocolate Day",
    "score": 90,
    "is_kid_friendly": true
  },
  {
    "id": 2,
    "original": "National Inspire Your Heart with Art Day",
    "score": 80,
    "is_kid_friendly": true
  },
  {
    "id": 3,
    "original": "National Backward Day",
    "score": 85,
    "is_kid_friendly": true
  },
  {
    "id": 4,
    "original": "National Brandy Alexander Day",
    "score": 35,
    "is_kid_friendly": false
  },
  {
    "id": 5,
    "original": "National Eat Brussels Sprouts Day",
    "score": 45,
    "is_kid_friendly": true
  },
  {
    "id": 6,
    "original": "National Fun at Work Day",
    "score": 90,
    "is_kid_friendly": true
  }
]