[
  {
    "id": "901",
    "title": "Buzzing About Our Busy Bee Friends",
    "story": "Every May 20, people around the world celebrate World Bee Day by learning about these amazing little workers! Schools organize bee-themed activities where kids discover how bees make honey and help flowers grow. Families plant bee-friendly flowers like sunflowers and lavender in their gardens. Many people wear yellow and black stripes to honor their favorite pollinators. Beekeepers open their hives for special tours, showing visitors how thousands of bees work together like a tiny city. Libraries host story times about busy bees, while nature centers teach kids the waggle dance that bees use to communicate. Some families even enjoy honey-sweetened treats to celebrate these incredible insects that help grow our food!",
    "activity_question": "What dance do bees use to communicate with each other?",
    "activity_choices": [
      "The waggle dance",
      "The buzz boogie",
      "The honey hop",
      "The flower flutter"
    ],
    "activity_answer": "The waggle dance",
    "bonus_fact": "A single bee visits about 2,000 flowers every day to collect nectar!",
    "optional_type": "bonus_fact",
    "categories": [
      "Days That Slay"
    ],
    "suitable_for_8_to_12_year_old": true,
    "score": 85
  },
  {
    "id": "902",
    "title": "Measuring Up on National Weights Day",
    "story": "Rulers, scales, and measuring cups get their moment to shine on May 20 during National Weights and Measures Day! People celebrate by appreciating all the tools that help us measure everything from ingredients for cookies to how tall we've grown. It's a day to thank the everyday heroes that make sure recipes work perfectly every time.",
    "activity_question": "What tools are celebrated on National Weights and Measures Day?",
    "activity_choices": [
      "Rulers, scales, and measuring cups",
      "Hammers, screwdrivers, and wrenches",
      "Paintbrushes, crayons, and markers",
      "Flying measuring tape robots"
    ],
    "activity_answer": "Rulers, scales, and measuring cups",
    "follow_up_question": "What would happen if we didn't have any measuring tools?",
    "optional_type": "follow_up_question",
    "categories": [
      "Days That Slay"
    ],
    "suitable_for_8_to_12_year_old": true,
    "score": 45
  }
]